{"cnpj": "01436319000208", "socios": [{"nome": "CINTIA CRISTINA MARIANO DOS SANTOS DE TOLEDO", "qualificacao": "Administrador", "entrada": "2017-09-13", "faixa_etaria": "Entre 41 a 50 anos", "candidaturas_tse": [], "parlamentares_homonimos": []}, {"nome": "HOTELARIA ALBA S.A.", "qualificacao": "Sócio", "entrada": "2017-09-13", "faixa_etaria": "Não se aplica", "candidaturas_tse": [], "parlamentares_homonimos": []}, {"nome": "LUMINAR PARTICIPACOES S.A.", "qualificacao": "Sócio", "entrada": "2021-08-26", "faixa_etaria": "Não se aplica", "candidaturas_tse": [], "parlamentares_homonimos": []}, {"nome": "VERIDIANA FURTADO", "qualificacao": "Administrador", "entrada": "2022-12-29", "faixa_etaria": "Entre 41 a 50 anos", "candidaturas_tse": [], "parlamentares_homonimos": []}]}