{"nodes": [{"id": "forn:33009945000204", "label": "PRODUTOS ROCHE QUIMICOS E FARMACEUTICOS S A", "tipo": "fornecedor", "grupo": null, "valor": 0}, {"id": "org:MINISTERIO DA SAUDE", "label": "MINISTERIO DA SAUDE", "tipo": "orgao", "grupo": null, "valor": 3078565304.41}, {"id": "org:SECRETARIA DE ESTADO DA SAUDE", "label": "SECRETARIA DE ESTADO DA SAUDE", "tipo": "orgao", "grupo": null, "valor": 62378375.42}, {"id": "org:SECRETARIA DE ESTADO DE PLANEJAMENTO E GESTAO", "label": "SECRETARIA DE ESTADO DE PLANEJAMENTO E GESTAO", "tipo": "orgao", "grupo": null, "valor": 52260215.88}, {"id": "org:FUNDO ESTADUAL DE SAUDE DO ESTADO DA BAHIA", "label": "FUNDO ESTADUAL DE SAUDE DO ESTADO DA BAHIA", "tipo": "orgao", "grupo": null, "valor": 24728277.55}, {"id": "org:ESTADO DO CEARA", "label": "ESTADO DO CEARA", "tipo": "orgao", "grupo": null, "valor": 15865981.49}, {"id": "org:SECRETARIA DE ESTADO DA SAUDE - SES", "label": "SECRETARIA DE ESTADO DA SAUDE - SES", "tipo": "orgao", "grupo": null, "valor": 13213516.24}, {"id": "org:COMANDO DA AERONAUTICA", "label": "COMANDO DA AERONAUTICA", "tipo": "orgao", "grupo": null, "valor": 7429372.05}, {"id": "org:MINISTERIO DA DEFESA", "label": "MINISTERIO DA DEFESA", "tipo": "orgao", "grupo": null, "valor": 3157415.09}, {"id": "org:COMANDO DA MARINHA", "label": "COMANDO DA MARINHA", "tipo": "orgao", "grupo": null, "valor": 3030024.0}, {"id": "org:HOSPITAL DAS CLINICAS DA FACULDADE DE MEDICINA DE RPUSP", "label": "HOSPITAL DAS CLINICAS DA FACULDADE DE MEDICINA DE RPUSP", "tipo": "orgao", "grupo": null, "valor": 1080831.6}, {"id": "org:COMANDO DO EXERCITO", "label": "COMANDO DO EXERCITO", "tipo": "orgao", "grupo": null, "valor": 161979.08}, {"id": "org:PROCURADORIA GERAL DE JUSTICA DE MINAS GERAIS", "label": "PROCURADORIA GERAL DE JUSTICA DE MINAS GERAIS", "tipo": "orgao", "grupo": null, "valor": 147131.4}, {"id": "org:ESTADO DO ESPIRITO SANTO", "label": "ESTADO DO ESPIRITO SANTO", "tipo": "orgao", "grupo": null, "valor": 94366.72}, {"id": "org:ESTADO DE GOIAS", "label": "ESTADO DE GOIAS", "tipo": "orgao", "grupo": null, "valor": 54739.2}, {"id": "org:FUNDACAO HOSPITALAR DO ESTADO DE MINAS GERAIS", "label": "FUNDACAO HOSPITALAR DO ESTADO DE MINAS GERAIS", "tipo": "orgao", "grupo": null, "valor": 29470.76}, {"id": "socio:ALBERTO FARAH D ANGELO", "label": "ALBERTO FARAH D ANGELO", "tipo": "socio", "grupo": "Diretor", "valor": 0}, {"id": "socio:FABIANA SIANO BOGGIO FARAH", "label": "FABIANA SIANO BOGGIO FARAH", "tipo": "socio", "grupo": "Diretor", "valor": 0}, {"id": "socio:LORICE FELISBINA FARIA SCALISE", "label": "LORICE FELISBINA FARIA SCALISE", "tipo": "socio", "grupo": "Presidente", "valor": 0}], "edges": [{"source": "org:MINISTERIO DA SAUDE", "target": "forn:33009945000204", "valor": 3078565304.41}, {"source": "org:SECRETARIA DE ESTADO DA SAUDE", "target": "forn:33009945000204", "valor": 62378375.42}, {"source": "org:SECRETARIA DE ESTADO DE PLANEJAMENTO E GESTAO", "target": "forn:33009945000204", "valor": 52260215.88}, {"source": "org:FUNDO ESTADUAL DE SAUDE DO ESTADO DA BAHIA", "target": "forn:33009945000204", "valor": 24728277.55}, {"source": "org:ESTADO DO CEARA", "target": "forn:33009945000204", "valor": 15865981.49}, {"source": "org:SECRETARIA DE ESTADO DA SAUDE - SES", "target": "forn:33009945000204", "valor": 13213516.24}, {"source": "org:COMANDO DA AERONAUTICA", "target": "forn:33009945000204", "valor": 7429372.05}, {"source": "org:MINISTERIO DA DEFESA", "target": "forn:33009945000204", "valor": 3157415.09}, {"source": "org:COMANDO DA MARINHA", "target": "forn:33009945000204", "valor": 3030024.0}, {"source": "org:HOSPITAL DAS CLINICAS DA FACULDADE DE MEDICINA DE RPUSP", "target": "forn:33009945000204", "valor": 1080831.6}, {"source": "org:COMANDO DO EXERCITO", "target": "forn:33009945000204", "valor": 161979.08}, {"source": "org:PROCURADORIA GERAL DE JUSTICA DE MINAS GERAIS", "target": "forn:33009945000204", "valor": 147131.4}, {"source": "org:ESTADO DO ESPIRITO SANTO", "target": "forn:33009945000204", "valor": 94366.72}, {"source": "org:ESTADO DE GOIAS", "target": "forn:33009945000204", "valor": 54739.2}, {"source": "org:FUNDACAO HOSPITALAR DO ESTADO DE MINAS GERAIS", "target": "forn:33009945000204", "valor": 29470.76}, {"source": "socio:ALBERTO FARAH D ANGELO", "target": "forn:33009945000204", "valor": 0, "rotulo": "sócio"}, {"source": "socio:FABIANA SIANO BOGGIO FARAH", "target": "forn:33009945000204", "valor": 0, "rotulo": "sócio"}, {"source": "socio:LORICE FELISBINA FARIA SCALISE", "target": "forn:33009945000204", "valor": 0, "rotulo": "sócio"}]}